{
  "5.1": {
    "alpine": "3.22",
    "debian": "bookworm",
    "downloadUrl": "https://www.redmine.org/releases/redmine-5.1.9.tar.gz",
    "ruby": {
      "version": "3.2"
    },
    "sha256": "cc0ddafa6fe6f5192236a27cec64e3466023a12c92c1da4abb680248639f678c",
    "variants": [
      "bookworm",
      "alpine3.22",
      "alpine3.21"
    ],
    "version": "5.1.9"
  },
  "6.0": {
    "alpine": "3.22",
    "debian": "bookworm",
    "downloadUrl": "https://www.redmine.org/releases/redmine-6.0.6.tar.gz",
    "ruby": {
      "version": "3.3"
    },
    "sha256": "b7ac2d28893806b8f4fbd1480b714be546614e830e2029d47a0bf26a352bb3fa",
    "variants": [
      "bookworm",
      "alpine3.22",
      "alpine3.21"
    ],
    "version": "6.0.6"
  }
}
